imgquad/__init__.py
imgquad/__main__.py
imgquad/imgquad.py
imgquad/jpegquality.py
imgquad/properties.py
imgquad/schematron.py
imgquad/shared.py
imgquad/profiles/beeldstudio-retro.xml
imgquad/profiles/mh-2025-tiff-300.xml
imgquad/profiles/mh-2025-tiff-600.xml
imgquad/profiles/mh-2025-tiff.xml
imgquad/schemas/beeldstudio-retro.sch
imgquad/schemas/mh-2025-tiff-300.sch
imgquad/schemas/mh-2025-tiff-600.sch
imgquad-0.1.6.dist-info/LICENSE
imgquad-0.1.6.dist-info/METADATA
imgquad-0.1.6.dist-info/WHEEL
imgquad-0.1.6.dist-info/entry_points.txt
imgquad-0.1.6.dist-info/top_level.txt
imgquad-0.1.6.dist-info/RECORD
