Metadata-Version: 2.1
Name: imgquad
Version: 0.1.6
Summary: IMaGe QUality Assessment for Digitisation batches
Home-page: https://github.com/KBNLresearch/imgquad
Download-URL: https://github.com/KBNLresearch/imgquad/archive/0.1.6.tar.gz
Author: Johan van der Knijff
Author-email: johan.vanderknijff@kb.nl
Maintainer: Johan van der Knijff
Maintainer-email: johan.vanderknijff@kb.nl
License: Apache License (https://www.apache.org/licenses/LICENSE-2.0)
Platform: POSIX
Platform: Windows
Classifier: Environment :: Console
Classifier: Programming Language :: Python :: 3
Requires-Python: >=3.8, <4
License-File: LICENSE
Requires-Dist: lxml
Requires-Dist: pillow >=9.0.0
Requires-Dist: setuptools
